urocksdb.libs/libsnappy-1125e350.so.1.3.0
urocksdb.libs/libgflags-b4c204a9.so.2.2.2
urocksdb.libs/libzstd-1518ed15.so.1.1.2
urocksdb/__init__.py
urocksdb/urocksdb.cpython-39-x86_64-linux-gnu.so
urocksdb/librocksdb.so.6.19.0
urocksdb/librocksdb.so.6
urocksdb/librocksdb.so
urocksdb-1.1.5.dist-info/RECORD
urocksdb-1.1.5.dist-info/METADATA
urocksdb-1.1.5.dist-info/top_level.txt
urocksdb-1.1.5.dist-info/WHEEL
urocksdb-1.1.5.dist-info/LICENSE
