Metadata-Version: 2.1
Name: urocksdb
Version: 1.1.5
Summary: python bindings to rocksdb with additional features
Home-page: UNKNOWN
Author: asif imran
Author-email: covariantmonkey@gmail.com
License: UNKNOWN
Platform: UNKNOWN
